i18nparse/__init__.py
i18nparse/i18nparse.py
i18nparse/version.py
i18nparse/locale/de/LC_MESSAGES/i18nparse.mo
i18nparse/locale/eo/LC_MESSAGES/i18nparse.mo
i18nparse/locale/es/LC_MESSAGES/i18nparse.mo
i18nparse/locale/fr/LC_MESSAGES/i18nparse.mo
i18nparse/locale/ka/LC_MESSAGES/i18nparse.mo
i18nparse/locale/nl/LC_MESSAGES/i18nparse.mo
i18nparse/locale/pt_BR/LC_MESSAGES/i18nparse.mo
i18nparse/locale/ro/LC_MESSAGES/i18nparse.mo
i18nparse/locale/sl/LC_MESSAGES/i18nparse.mo
i18nparse/locale/sr/LC_MESSAGES/i18nparse.mo
i18nparse/locale/sv/LC_MESSAGES/i18nparse.mo
i18nparse/locale/uk/LC_MESSAGES/i18nparse.mo
i18nparse-1.0.3.dist-info/METADATA
i18nparse-1.0.3.dist-info/WHEEL
i18nparse-1.0.3.dist-info/licenses/LICENSE
i18nparse-1.0.3.dist-info/RECORD
