Metadata-Version: 2.4
Name: i18nparse
Version: 1.0.3
Summary: Provides translations for argparse module
Project-URL: Changelog, https://github.com/s-ball/i18nparse/blob/master/CHANGES.txt
Project-URL: Homepage, https://github.com/s-ball/i18nparse
Author-email: s-ball <s-ball@laposte.net>
License-Expression: MIT
License-File: LICENSE
Classifier: Development Status :: 5 - Production/Stable
Classifier: Environment :: Console
Classifier: Intended Audience :: Developers
Classifier: License :: OSI Approved :: MIT License
Classifier: Operating System :: OS Independent
Classifier: Programming Language :: Python :: 3
Classifier: Programming Language :: Python :: 3.9
Classifier: Programming Language :: Python :: 3.10
Classifier: Programming Language :: Python :: 3.11
Classifier: Programming Language :: Python :: 3.12
Classifier: Programming Language :: Python :: 3.13
Classifier: Topic :: Software Development :: Localization
Requires-Python: >=3.9
